Example_Ckt/exampleCkt.v
module example(A,B,C,D,E,F,Y);
  input A,B,C,D,E,F;
  output Y;
  wire t1, t2, t3, t4, Y;
  not #1 G0(t4,B);
  nand #1 G1(t1,A,B);
  and #1 G2(t2,C,t4,D);
  nor #1 G3(t3,E,F);
  nand #1 G4(Y,t1,t2,t3);
endmodule

Example_Ckt/exampleCkt_tb.v
`include "exampleCkt.v"
module testbench;
  reg A,B,C,D,E,F;
  wire Y;
  example DUT(A,B,C,D,E,F,Y);
  initial begin
    $dumpfile("exampleCkt.vcd");
    $dumpvars(0,testbench);
    $monitor($time,"A=%b, B=%b, C=%b, D=%b, E=%b, F=%b, Y=%b",A,B,C,D,E,F,Y);
    #5 A = 1; B = 0; C = 0; D = 1; E = 0; F = 0;
    #5 A = 0; B = 0; C = 1; D = 1; E = 0; F = 0;
    #5 A = 1; C = 0;
  end
endmodule

Example_Ckt/exampleCkt.vcd
$date
	Sat Dec 14 12:52:54 2024
$end
$version
	Icarus Verilog
$end
$timescale
	1s
$end
$scope module testbench $end
$var wire 1 ! Y $end
$var reg 1 " A $end
$var reg 1 # B $end
$var reg 1 $ C $end
$var reg 1 % D $end
$var reg 1 & E $end
$var reg 1 ' F $end
$scope module DUT $end
$var wire 1 ( A $end
$var wire 1 ) B $end
$var wire 1 * C $end
$var wire 1 + D $end
$var wire 1 , E $end
$var wire 1 - F $end
$var wire 1 ! Y $end
$var wire 1 . t1 $end
$var wire 1 / t2 $end
$var wire 1 0 t3 $end
$var wire 1 1 t4 $end
$upscope $end
$upscope $end
$enddefinitions $end
#0
$dumpvars
x1
x0
x/
x.
x-
x,
x+
x*
x)
x(
x'
x&
x%
x$
x#
x"
x!
$end
#5
0'
0-
0&
0,
1%
1+
0$
0*
0#
0)
1"
1(
#6
10
0/
11
1.
#7
1!
#10
1$
1*
0"
0(
#11
1/
#12
0!
#15
0$
0*
1"
1(
#16
0/
#17
1!
